CHANGES.txt
LICENSE.txt
MANIFEST.in
README.txt
setup.py
DynamodbFdw.egg-info/PKG-INFO
DynamodbFdw.egg-info/SOURCES.txt
DynamodbFdw.egg-info/dependency_links.txt
DynamodbFdw.egg-info/requires.txt
DynamodbFdw.egg-info/top_level.txt
bin/install-multicorn-9.1.sh
docs/README.txt
dynamodbfdw/__init__.py
dynamodbfdw/dynamodbfdw.py