Metadata-Version: 1.0
Name: DynamodbFdw
Version: 0.1.1
Summary: Postgresql Foregin Data Wrapper mapping Amazon DynamoDB
Home-page: https://github.com/avances123/dynamodb_fdw
Author: Fabio Rueda
Author-email: avances123@gmail.com
License: LICENSE.txt
Platform: UNKNOWN
